Metadata-Version: 1.2
Name: mturk-crowd-beta-client
Version: 1.0.0
Summary: A client for the MTurk Crowd REST API
Home-page: https://github.com/awslabs/mturk-crowd-beta-client-python
Author: Amazon Mechanical Turk
Author-email: mturk-requester-preview@amazon.com
License: Apache License 2.0
Keywords: mturk-crowd-beta-client
Platform: UNKNOWN
Classifier: Development Status :: 5 - Production/Stable
Classifier: License :: OSI Approved :: Apache Software License
Classifier: Programming Language :: Python
Classifier: Programming Language :: Python :: 2
Classifier: Programming Language :: Python :: 2.7
Classifier: Programming Language :: Python :: 3
Requires-Python: >=2.7, <4
